odoo_addons_parser/__init__.py
odoo_addons_parser/code.py
odoo_addons_parser/module.py
odoo_addons_parser/odoo.py
odoo_addons_parser/repository.py
odoo_addons_parser/tests/__init__.py
odoo_addons_parser/tests/common.py
odoo_addons_parser/tests/test_module.py
odoo_addons_parser/tests/test_odoo.py
odoo_addons_parser/tests/test_repository.py
odoo_addons_parser/tests/repo/module_test/__init__.py
odoo_addons_parser/tests/repo/module_test/__manifest__.py
odoo_addons_parser/tests/repo/module_test/models/__init__.py
odoo_addons_parser/tests/repo/module_test/models/res_partner.py
odoo_addons_parser/tests/repo/module_test/models/res_users.py
odoo_addons_parser/tests/repo/module_test/views/res_partner.xml
odoo_addons_parser-0.5.dist-info/licenses/LICENSE
odoo_addons_parser-0.5.dist-info/METADATA
odoo_addons_parser-0.5.dist-info/WHEEL
odoo_addons_parser-0.5.dist-info/top_level.txt
odoo_addons_parser-0.5.dist-info/RECORD
