Metadata-Version: 2.4
Name: odoo-addons-parser
Version: 0.5
Summary: Collect data from Odoo module folders.
Author: Sébastien Alix
License:                    GNU LESSER GENERAL PUBLIC LICENSE
Project-URL: homepage, https://github.com/sebalix/odoo-addons-parser
Project-URL: documentation, https://github.com/sebalix/odoo-addons-parser
Project-URL: repository, https://github.com/sebalix/odoo-addons-parser
Keywords: odoo,oca,analyze,parser,collect,modules,addons
Classifier: License :: OSI Approved :: GNU Lesser General Public License v3 (LGPLv3)
Classifier: Programming Language :: Python :: 3
Classifier: Framework :: Odoo
Requires-Python: >=3.9
License-File: LICENSE
Requires-Dist: pygount<1.7.0
Provides-Extra: test
Requires-Dist: pytest; extra == "test"
Requires-Dist: coverage; extra == "test"
Dynamic: license-file
